dc_helpers/__init__.py
dc_helpers/ch.py
dc_helpers/connections.py
dc_helpers/dev_cache.py
dc_helpers/elapsed.py
dc_helpers/error.py
dc_helpers/google_sheets.py
dc_helpers/log.py
dc_helpers/logging_helpers.py
dc_helpers/mailer.py
dc_helpers/pg.py
dc_helpers/restart.py
dc_helpers/rps.py
dc_helpers/secrets.py
dc_helpers/tempdir.py
dc_helpers-0.6.3.dist-info/METADATA
dc_helpers-0.6.3.dist-info/WHEEL
dc_helpers-0.6.3.dist-info/top_level.txt
dc_helpers-0.6.3.dist-info/RECORD
