Metadata-Version: 2.1
Name: dc-helpers
Version: 0.6.3
Summary: DC utility functions and classes
Home-page: UNKNOWN
Author: Viktor Makarov
Author-email: viktor.makarov@corp.mail.ru
License: UNKNOWN
Keywords: utility
Platform: UNKNOWN
Classifier: Development Status :: 4 - Beta
Classifier: Programming Language :: Python :: 3
Classifier: Operating System :: OS Independent
